circus/__init__.py
circus/_patch.py
circus/arbiter.py
circus/circusctl.py
circus/circusd.py
circus/client.py
circus/config.py
circus/consumer.py
circus/controller.py
circus/exc.py
circus/fixed_threading.py
circus/pidfile.py
circus/process.py
circus/sighandler.py
circus/sockets.py
circus/util.py
circus/watcher.py
circus/commands/__init__.py
circus/commands/addwatcher.py
circus/commands/base.py
circus/commands/decrproc.py
circus/commands/dstats.py
circus/commands/errors.py
circus/commands/get.py
circus/commands/globaloptions.py
circus/commands/incrproc.py
circus/commands/ipythonshell.py
circus/commands/kill.py
circus/commands/list.py
circus/commands/listen.py
circus/commands/listsockets.py
circus/commands/numprocesses.py
circus/commands/numwatchers.py
circus/commands/options.py
circus/commands/quit.py
circus/commands/reload.py
circus/commands/reloadconfig.py
circus/commands/restart.py
circus/commands/rmwatcher.py
circus/commands/sendsignal.py
circus/commands/set.py
circus/commands/start.py
circus/commands/stats.py
circus/commands/status.py
circus/commands/stop.py
circus/commands/util.py
circus/green/__init__.py
circus/green/arbiter.py
circus/green/client.py
circus/green/consumer.py
circus/green/controller.py
circus/green/sighandler.py
circus/plugins/__init__.py
circus/plugins/_statsd.py
circus/plugins/command_reloader.py
circus/plugins/flapping.py
circus/plugins/http_observer.py
circus/plugins/redis_observer.py
circus/plugins/resource_watcher.py
circus/plugins/statsd.py
circus/plugins/watchdog.py
circus/stats/__init__.py
circus/stats/client.py
circus/stats/collector.py
circus/stats/publisher.py
circus/stats/streamer.py
circus/stream/__init__.py
circus/stream/file_stream.py
circus/stream/redirector.py
kantoku-0.18.2.dist-info/entry_points.txt
kantoku-0.18.2.dist-info/licenses/LICENSE
kantoku-0.18.2.dist-info/WHEEL
kantoku-0.18.2.dist-info/METADATA
kantoku-0.18.2.dist-info/RECORD
