Metadata-Version: 2.4
Name: kantoku
Version: 0.18.2
Summary: Circus is a program that will let you run and watch multiple processes and sockets.
Author-email: Mozilla Foundation & contributors <services-dev@lists.mozila.org>, BentoML Team <team@bentoml.com>
Requires-Python: >=3.7
Classifier: Development Status :: 5 - Production/Stable
Classifier: License :: OSI Approved :: Apache Software License
Classifier: Operating System :: POSIX :: Linux
Classifier: Operating System :: MacOS :: MacOS X
Classifier: Operating System :: Microsoft :: Windows
Classifier: Programming Language :: Python
Classifier: Programming Language :: Python :: 3.7
Classifier: Programming Language :: Python :: 3.8
Classifier: Programming Language :: Python :: 3.9
Classifier: Programming Language :: Python :: 3.10
Classifier: Programming Language :: Python :: 3.11
Classifier: Programming Language :: Python :: 3.12
Classifier: Programming Language :: Python :: 3.13
License-File: LICENSE
Requires-Dist: psutil
Requires-Dist: pyzmq>=17.0
Requires-Dist: tornado>=5.0.2
Requires-Dist: coverage ; extra == "test"
Requires-Dist: flake8 ; extra == "test"
Requires-Dist: gevent ; extra == "test"
Requires-Dist: mock ; extra == "test"
Requires-Dist: pytest ; extra == "test"
Requires-Dist: pytest-cov ; extra == "test"
Requires-Dist: pyyaml ; extra == "test"
Requires-Dist: tox ; extra == "test"
Project-URL: Documentation, https://circus.readthedocs.io
Project-URL: Source, https://github.com/bentoml/kantoku
Provides-Extra: test
